oxapy/__init__.py
oxapy/__init__.pyi
oxapy/exceptions/__init__.pyi
oxapy/jwt/__init__.pyi
oxapy/oxapy.pypy311-pp73-x86_64-linux-gnu.so
oxapy/serializer/__init__.pyi
oxapy/templating/__init__.pyi
oxapy-0.8.0.dist-info/METADATA
oxapy-0.8.0.dist-info/WHEEL
oxapy-0.8.0.dist-info/licenses/LICENSE
oxapy.libs/libgcc_s-6d2d9dc8.so.1
oxapy-0.8.0.dist-info/RECORD
